README.rst
_description.org
lh-agpl3-LICENSE.txt
pyproject.toml
setup.py
bin/bx-bases-bisosCore.py
bisos/__init__.py
bisos.coreDist.egg-info/PKG-INFO
bisos.coreDist.egg-info/SOURCES.txt
bisos.coreDist.egg-info/dependency_links.txt
bisos.coreDist.egg-info/not-zip-safe
bisos.coreDist.egg-info/requires.txt
bisos.coreDist.egg-info/top_level.txt
bisos/coreDist/__init__.py
bisos/coreDist/thisPkg.py
bisos/coreDist-config/placeHolderForFPs
bisos/coreDist-root/adoptedDistros/MAEMO/OS2008/debPkgs-PreLP-Priv0Server.include
bisos/coreDist-root/adoptedDistros/MAEMO/OS2008/hildon-application-manager.list.WIDE
bisos/coreDist-root/adoptedDistros/MAEMO/OS2008/rx-44.kbd
bisos/coreDist-root/adoptedDistros/debian/7/debPkgs/debPkgs-DistVirgin.exclude
bisos/coreDist-root/adoptedDistros/debian/7/debPkgs/debPkgs-DistVirgin.exclude.sorted
bisos/coreDist-root/adoptedDistros/debian/7/debPkgs/debPkgs-DistVirgin.include
bisos/coreDist-root/adoptedDistros/debian/7/debPkgs/debPkgs-DistVirgin.include.sorted
bisos/coreDist-root/adoptedDistros/debian/7/debPkgs/debPkgs-DistVirgin.list
bisos/coreDist-root/adoptedDistros/debian/7/debPkgs/debPkgs-DistVirgin.list.110413232956
bisos/coreDist-root/adoptedDistros/debian/7/debPkgs/debPkgs-FinalLP-Priv0Server.include
bisos/coreDist-root/adoptedDistros/debian/7/debPkgs/debPkgs-FinalLP-Priv0Server.include.sorted
bisos/coreDist-root/adoptedDistros/debian/7/debPkgs/debPkgs-FinalLP-Priv0Server.list
bisos/coreDist-root/adoptedDistros/debian/7/debPkgs/debPkgs-FinalLP.exclude
bisos/coreDist-root/adoptedDistros/debian/7/debPkgs/debPkgs-FinalLP.exclude.sorted
bisos/coreDist-root/adoptedDistros/debian/7/debPkgs/debPkgs-PreLP-Priv0Server.include
bisos/coreDist-root/adoptedDistros/debian/7/debPkgs/debPkgs-PreLP-Priv0Server.include.sorted
bisos/coreDist-root/adoptedDistros/debian/7/debPkgs/debPkgs-PreLP-Priv0Server.list
bisos/coreDist-root/adoptedDistros/debian/7/debPkgs/debPkgs-PreLP.exclude
bisos/coreDist-root/adoptedDistros/debian/7/debPkgs/debPkgs-PreLP.exclude.sorted
bisos/coreDist-root/adoptedDistros/debian/7/debPkgs/distRepositorySrc
bisos/coreDist-root/adoptedDistros/debian/7/debPkgs/pubKey.sh
bisos/coreDist-root/adoptedDistros/debian/7/debPkgs/source.list+backports
